r_mutex/__init__.py
r_mutex/base.py
r_mutex/client.py
r_mutex/manager.py
r_mutex-1.1.0.dist-info/METADATA
r_mutex-1.1.0.dist-info/WHEEL
r_mutex-1.1.0.dist-info/top_level.txt
r_mutex-1.1.0.dist-info/RECORD
