Metadata-Version: 2.2
Name: r-mutex
Version: 1.1.0
Summary: A simple Redis based lock
Home-page: https://github.com/JadoreThompson/r-mutex
Author: JadoreThompson
Requires-Python: >=3.12
Requires-Dist: redis
Dynamic: author
Dynamic: description
Dynamic: home-page
Dynamic: requires-dist
Dynamic: requires-python
Dynamic: summary
